heinlein_des/__init__.py
heinlein_des/config.json
heinlein_des/des.py
heinlein_des/regions.reg
heinlein_des-0.3.1.dist-info/METADATA
heinlein_des-0.3.1.dist-info/WHEEL
heinlein_des-0.3.1.dist-info/RECORD
