Metadata-Version: 2.3
Name: heinlein_des
Version: 0.3.1
Summary: DES plugin for heinlein
Author: Patrick Wells
Author-email: patrick@astropatty.com
Requires-Python: >=3.11
Classifier: Programming Language :: Python :: 3
Classifier: Programming Language :: Python :: 3.11
Classifier: Programming Language :: Python :: 3.12
Classifier: Programming Language :: Python :: 3.13
